TMarSel/TMarSel.py
TMarSel/__init__.py
tmarsel-0.1.1.dist-info/METADATA
tmarsel-0.1.1.dist-info/WHEEL
tmarsel-0.1.1.dist-info/entry_points.txt
tmarsel-0.1.1.dist-info/licenses/LICENSE
tmarsel-0.1.1.dist-info/RECORD
