Metadata-Version: 2.4
Name: TMarSel
Version: 0.1.1
Summary: select gene families as markers for microbial phylogenomics
Project-URL: Homepage, https://github.com/HSecaira/TMarSel
Project-URL: Documentation, https://github.com/HSecaira/TMarSel/blob/main/README.md
Project-URL: Repository, https://github.com/HSecaira/TMarSel.git
Project-URL: Issues, https://github.com/HSecaira/TMarSel/issues
Author-email: Henry Secaira Morocho <henrry.secairamorocho@gmail.com>, Qiyun Zhu <qiyunzhu@gmail.com>
Maintainer-email: Henry Secaira Morocho <henrry.secairamorocho@gmail.com>
License: BSD 3-Clause License
License-File: LICENSE
Keywords: bioinformatics,metagenomics,microbiome,phylogenomics
Classifier: Development Status :: 2 - Pre-Alpha
Classifier: Intended Audience :: Science/Research
Classifier: License :: OSI Approved :: BSD License
Classifier: Operating System :: OS Independent
Classifier: Programming Language :: Python
Classifier: Programming Language :: Python :: 3
Classifier: Programming Language :: Python :: 3 :: Only
Classifier: Topic :: Scientific/Engineering
Classifier: Topic :: Scientific/Engineering :: Bio-Informatics
Requires-Python: >=3.9
Requires-Dist: numpy
Requires-Dist: pandas
Requires-Dist: scipy
Requires-Dist: tqdm
